LICENSE
README.md
setup.py
lib/hashio/__init__.py
lib/hashio/cache.py
lib/hashio/cli.py
lib/hashio/config.py
lib/hashio/encoder.py
lib/hashio/exporter.py
lib/hashio/logger.py
lib/hashio/utils.py
lib/hashio/worker.py
lib/hashio.egg-info/PKG-INFO
lib/hashio.egg-info/SOURCES.txt
lib/hashio.egg-info/dependency_links.txt
lib/hashio.egg-info/entry_points.txt
lib/hashio.egg-info/not-zip-safe
lib/hashio.egg-info/requires.txt
lib/hashio.egg-info/top_level.txt
tests/test_hashio.py
tests/test_lock.py
tests/test_retry_fail.py
tests/test_retry_success.py