Metadata-Version: 2.1
Name: hashio
Version: 0.4.10
Summary: Custom file and directory checksum tool
Home-page: http://github.com/rsgalloway/hashio
Author: Ryan Galloway
Author-email: ryan@rsgalloway.com
License: BSD 3-Clause License
Classifier: Development Status :: 4 - Beta
Classifier: Intended Audience :: Developers
Classifier: Topic :: Software Development :: Libraries
Classifier: Programming Language :: Python :: 3
Classifier: Programming Language :: Python :: 3.6
Classifier: Programming Language :: Python :: 3.7
Classifier: Programming Language :: Python :: 3.8
Classifier: Programming Language :: Python :: 3.9
Classifier: Programming Language :: Python :: 3.10
Classifier: Programming Language :: Python :: 3.11
Requires-Python: >=3.6
License-File: LICENSE
Requires-Dist: lxml==5.3.0
Requires-Dist: tqdm==4.67.1
Requires-Dist: xxhash==3.5.0
